{"is_source_file": true, "format": "JavaScript (React JSX)", "description": "This file defines a React functional component named GameStatus that displays the current game status in a Tic-Tac-Toe game. It accepts a 'status' prop and renders it inside a styled div with accessibility attributes.", "external_files": [], "external_methods": [], "published": ["GameStatus"], "classes": [], "methods": [{"name": "GameStatus({ status })", "description": "Functional React component that displays the game status text passed via props.", "scope": "", "scopeKind": ""}], "calls": [], "search-terms": ["GameStatus", "React", "jsx", "status display", "tic tac toe"], "state": 2, "file_id": 15, "knowledge_revision": 34, "git_revision": "449c2ec63adb15ee6eacf78d0213ba6577ca8118", "ctags": [{"_type": "tag", "name": "GameStatus", "path": "/home/kavia/workspace/code-generation/browser-tic-tac-toe-297256-297265/tic_tac_toe_frontend/src/components/GameStatus.jsx", "pattern": "/^export default function GameStatus({ status }) {$/", "language": "JavaScript", "kind": "function", "signature": "({ status })"}], "hash": "db693662c9d3c5abe48383466eb159b5", "format-version": 4, "code-base-name": "tic_tac_toe_frontend", "filename": "tic_tac_toe_frontend/src/components/GameStatus.jsx", "revision_history": [{"34": "449c2ec63adb15ee6eacf78d0213ba6577ca8118"}]}